nnm/__init__.py
nnm/version.py
nnm/checkpoint/__init__.py
nnm/checkpoint/ema.py
nnm/checkpoint/saver.py
nnm/dataset/__init__.py
nnm/dataset/mnist.py
nnm/dataset/swiss_roll.py
nnm/diffusion/README.md
nnm/diffusion/swiss_roll_ddpm.py
nnm/gan/gan.py
nnm/layers/__init__.py
nnm/layers/attention.py
nnm/layers/drop.py
nnm/layers/norm.py
nnm/layers/rope.py
nnm/layers/rwkv.py
nnm/layers/vit.py
nnm/metrics/__init__.py
nnm/metrics/belu.py
nnm/models/__init__.py
nnm/models/davit.py
nnm/models/fastvit.py
nnm/models/florence.py
nnm/models/qwen2.py
nnm/utils/__init__.py
nnm/utils/grad.py
nnm/utils/param.py
nnm/vae/mnist_vae.py
nnm-0.0.4.dist-info/METADATA
nnm-0.0.4.dist-info/WHEEL
nnm-0.0.4.dist-info/licenses/LICENSE
nnm-0.0.4.dist-info/RECORD
