Metadata-Version: 2.4
Name: nnm
Version: 0.0.4
Summary: Neural Network Models
Project-URL: Homepage, https://github.com/jiauzhang/nnm
Author-email: Jiau Zhang <jiauzhang@163.com>
License:                     GNU GENERAL PUBLIC LICENSE
License-File: LICENSE
Keywords: Artificial Intelligence,Deep Learning,PyTorch
Classifier: Intended Audience :: Developers
Classifier: License :: OSI Approved :: GNU General Public License v3 (GPLv3)
Classifier: Programming Language :: Python :: 3.10
Classifier: Topic :: Scientific/Engineering :: Artificial Intelligence
Requires-Python: >=3.10
Requires-Dist: conippets>=0.1.8
Requires-Dist: fakeset
Requires-Dist: numpy
Requires-Dist: torch
Provides-Extra: dev
Requires-Dist: pytest==8.3.4; extra == 'dev'
Requires-Dist: transformers==4.51.3; extra == 'dev'
